kathekon/__init__.py
kathekon/cli.py
kathekon/data/quotes.db
kathekon-0.0.7.dist-info/LICENSE
kathekon-0.0.7.dist-info/METADATA
kathekon-0.0.7.dist-info/WHEEL
kathekon-0.0.7.dist-info/entry_points.txt
kathekon-0.0.7.dist-info/top_level.txt
kathekon-0.0.7.dist-info/RECORD
