Metadata-Version: 2.2
Name: kathekon
Version: 0.0.7
Summary: kathekon is a Python library and CLI tool for fetching Stoic quotes with interpretations.
Home-page: https://github.com/janthmueller/kathekon
Author: Jan T. Müller
Author-email: mail@jantmueller.com
License: MIT
Project-URL: Documentation, https://github.com/janthmueller/kathekon/blob/main/README.md
Project-URL: Source, https://github.com/janthmueller/kathekon
Project-URL: Tracker, https://github.com/janthmueller/kathekon/issues
Classifier: Intended Audience :: Developers
Classifier: Topic :: Utilities
Classifier: License :: OSI Approved :: MIT License
Classifier: Operating System :: OS Independent
Classifier: Programming Language :: Python :: 3
Classifier: Programming Language :: Python :: 3.7
Classifier: Programming Language :: Python :: 3.8
Classifier: Programming Language :: Python :: 3.9
Classifier: Programming Language :: Python :: 3.10
Classifier: Programming Language :: Python :: 3.11
Requires-Python: >=3.7
License-File: LICENSE
Requires-Dist: rich
Provides-Extra: openai
Requires-Dist: rich; extra == "openai"
Requires-Dist: openai>=1.57.0; extra == "openai"
Provides-Extra: all
Requires-Dist: rich; extra == "all"
Requires-Dist: openai>=1.57.0; extra == "all"
Dynamic: author
Dynamic: author-email
Dynamic: classifier
Dynamic: description
Dynamic: description-content-type
Dynamic: home-page
Dynamic: license
Dynamic: project-url
Dynamic: provides-extra
Dynamic: requires-dist
Dynamic: requires-python
Dynamic: summary
